{
  "name": "Ice Cavern 01",
  "tileSize": 64,
  "width": 12,
  "height": 10,
  "par": 3,
  "objective": "Survive the opening rush, crush every raider with the ice blocks, then reach the glowing exit.",
  "playerSpawn": { "x": 5, "y": 6 },
  "blocks": [
    { "x": 3, "y": 3 },
    { "x": 4, "y": 3 },
    { "x": 5, "y": 4 },
    { "x": 6, "y": 3 },
    { "x": 7, "y": 3 }
  ],
  "enemies": [
    { "type": "basic", "x": 3, "y": 1 },
    { "type": "basic", "x": 5, "y": 1 },
    { "type": "basic", "x": 7, "y": 1 }
  ],
  "goals": [
    { "x": 9, "y": 6 }
  ],
  "walls": [
    { "x": 0, "y": 0 }, { "x": 1, "y": 0 }, { "x": 2, "y": 0 }, { "x": 3, "y": 0 }, { "x": 4, "y": 0 }, { "x": 5, "y": 0 }, { "x": 6, "y": 0 }, { "x": 7, "y": 0 }, { "x": 8, "y": 0 }, { "x": 9, "y": 0 }, { "x": 10, "y": 0 },
    { "x": 0, "y": 1 }, { "x": 10, "y": 1 },
    { "x": 0, "y": 2 }, { "x": 10, "y": 2 },
    { "x": 0, "y": 3 }, { "x": 10, "y": 3 },
    { "x": 0, "y": 4 }, { "x": 10, "y": 4 },
    { "x": 0, "y": 5 }, { "x": 10, "y": 5 },
    { "x": 0, "y": 6 }, { "x": 10, "y": 6 },
    { "x": 0, "y": 7 }, { "x": 10, "y": 7 },
    { "x": 0, "y": 8 }, { "x": 1, "y": 8 }, { "x": 2, "y": 8 }, { "x": 3, "y": 8 }, { "x": 4, "y": 8 }, { "x": 5, "y": 8 }, { "x": 6, "y": 8 }, { "x": 7, "y": 8 }, { "x": 8, "y": 8 }, { "x": 9, "y": 8 }, { "x": 10, "y": 8 },
    { "x": 2, "y": 2 }, { "x": 5, "y": 2 }, { "x": 8, "y": 2 },
    { "x": 2, "y": 5 }, { "x": 5, "y": 5 }, { "x": 8, "y": 5 }
  ]
}
